ichigo/__init__.py
ichigo/__main__.py
ichigo/config.py
ichigo/idlbridge.py
ichigo/images.py
ichigo/plots.py
ichigo/settings.ini
ichigo/settings.types.ini
ichigo/strmanip.py
ichigo/calc/__init__.py
ichigo/calc/buffers.py
ichigo/calc/cmat.py
ichigo/calc/psfs.py
ichigo/calc/pupils.py
ichigo/calc/wavefront.py
ichigo/calc/zernikes.py
ichigo/calc/cacofoni/__init__.py
ichigo/calc/cacofoni/make_cacofoni.py
ichigo/calc/cacofoni/mc/_compute_actuator_fft.py
ichigo/calc/cacofoni/mc/_compute_fft.py
ichigo/calc/cacofoni/mc/_compute_laplacian.py
ichigo/calc/cacofoni/mc/_load_and_log_telemetry.py
ichigo/calc/cacofoni/mc/calc_samp_freq.py
ichigo/calc/cacofoni/mc/config.py
ichigo/calc/cacofoni/mc/deriv2D.py
ichigo/calc/cacofoni/mc/file_utils.py
ichigo/calc/cacofoni/mc/find_peak_freq.py
ichigo/managers/__init__.py
ichigo/managers/felixloop.py
ichigo/managers/manager.py
ichigo/managers/script.py
ichigo/managers/state.py
ichigo/resources/.DS_Store
ichigo/resources/cmat.20241107b.LS.fits
ichigo/resources/cmat.pistonfilter.20241107b.LS.fits
ichigo/resources/ehuhosts.json
ichigo/resources/example-hosts.json
ichigo/resources/imakaparm.txt
ichigo/resources/piston_filter-matrix.fits
ichigo/resources/rtc_in.txt
ichigo/resources/dm/.DS_Store
ichigo/resources/dm/a2z.20240409b.fits
ichigo/resources/dm/a2z.37withpiston.fits
ichigo/resources/dm/a2z.empirical_norm_piston0.20250408b.fits
ichigo/resources/dm/bim_20240409b-96x96-pistonfree.fits
ichigo/resources/dm/bim_20240409b-96x96.fits
ichigo/resources/dm/dm_flat.fits
ichigo/resources/dm/irtf-1_infl_func_20240409b.fits
ichigo/resources/dm/irtf-1_infl_func_20250404b.fits
ichigo/resources/dm/irtf-1_infl_func_96x96.20250404b.fits
ichigo/resources/dm/mm.20240409b.fits
ichigo/resources/dm/mm2a_norm.20240409b.fits
ichigo/resources/dm/mm2s.20250417.fits
ichigo/resources/dm/mm2s_norm.20250417.fits
ichigo/resources/dm/pup_ASM-HASO_96x96.fits
ichigo/resources/dm/z2a.20240409b.fits
ichigo/resources/dm/z2a.37withpiston.fits
ichigo_imaka-0.0.3.dist-info/METADATA
ichigo_imaka-0.0.3.dist-info/WHEEL
ichigo_imaka-0.0.3.dist-info/entry_points.txt
ichigo_imaka-0.0.3.dist-info/top_level.txt
ichigo_imaka-0.0.3.dist-info/RECORD
