Metadata-Version: 2.4
Name: ichigo-imaka
Version: 0.0.3
Summary: Object-oriented scripting package for the imaka RTC
Author-email: Ellen Lee <ellenlee@hawaii.edu>
License: MIT License
Project-URL: Homepage, https://github.com/ellenle3/ichigo-imaka
Classifier: Programming Language :: Python :: 3.10
Classifier: License :: OSI Approved :: MIT License
Classifier: Operating System :: OS Independent
Requires-Python: >=3.10
Requires-Dist: numpy<=1.26.4
Requires-Dist: astropy
Requires-Dist: scipy
Requires-Dist: matplotlib
Requires-Dist: hcipy
Requires-Dist: paramiko
Requires-Dist: pillow
Requires-Dist: jupyter
Requires-Dist: pyautogui
Requires-Dist: opencv-python
Requires-Dist: importlib_resources
Provides-Extra: fnf
Requires-Dist: configobj; extra == "fnf"
Requires-Dist: scikit-image; extra == "fnf"
Requires-Dist: ipdb; extra == "fnf"
Provides-Extra: docs
Requires-Dist: sphinx==8.1.3; extra == "docs"
Requires-Dist: furo==2024.8.6; extra == "docs"
Requires-Dist: sphinx-copybutton==0.5.2; extra == "docs"
Requires-Dist: nbsphinx==0.9.6; extra == "docs"
Requires-Dist: pandoc; extra == "docs"
